form_analyzer/__init__.py
form_analyzer/analyze.py
form_analyzer/conversion.py
form_analyzer/filters.py
form_analyzer/form_parser.py
form_analyzer/textract.py
form_analyzer/selectors/__init__.py
form_analyzer/selectors/base.py
form_analyzer/selectors/multi_select.py
form_analyzer/selectors/select_base.py
form_analyzer/selectors/single_select.py
form_analyzer/selectors/text_fields.py
form_analyzer-0.1.2.dist-info/LICENSE
form_analyzer-0.1.2.dist-info/METADATA
form_analyzer-0.1.2.dist-info/WHEEL
form_analyzer-0.1.2.dist-info/top_level.txt
form_analyzer-0.1.2.dist-info/RECORD
