Metadata-Version: 2.1
Name: form-analyzer
Version: 0.1.2
Summary: Python package to analyze scanned questionnaires and forms with AWS Textract and convert the results to an XLSX.
Home-page: https://github.com/futsch1/form-analyzer
Author: Florian Fetz
Author-email: florian.fetz@gmail.com
License: MIT
Project-URL: Documentation, http://form-analyzer.rtfd.io
Keywords: textract,AWS,form,questionnaire,xlsx,excel
Classifier: License :: OSI Approved :: MIT License
Classifier: Programming Language :: Python :: 3
Classifier: Topic :: Scientific/Engineering :: Information Analysis
Classifier: Topic :: Scientific/Engineering :: Image Processing
Requires-Python: >=3.7
License-File: LICENSE
Requires-Dist: boto3
Requires-Dist: amazon-textract-caller
Requires-Dist: amazon-textract-response-parser
Requires-Dist: pdf2image
Requires-Dist: openpyxl
Provides-Extra: dev
Requires-Dist: coverage ; extra == 'dev'
Provides-Extra: doc
Requires-Dist: sphinx ; extra == 'doc'
Requires-Dist: myst-parser ; extra == 'doc'
